blabing.py
blabing-0.2.1.data/scripts/bla
blabing-0.2.1.data/scripts/lhl
blabing-0.2.1.data/scripts/standalone_ldap.sh
blabing-0.2.1.dist-info/LICENSE.txt
blabing-0.2.1.dist-info/METADATA
blabing-0.2.1.dist-info/WHEEL
blabing-0.2.1.dist-info/top_level.txt
blabing-0.2.1.dist-info/RECORD
