Metadata-Version: 2.1
Name: blabing
Version: 0.2.1
Summary: Building a convenient CLI on top of LDAP3
Author-email: Julien Tayon <julien@tayon.net>
Maintainer-email: Julien Tayon <julien@tayon.net>
License: PYTHON SOFTWARE FOUNDATION LICENSE VERSION 2
Project-URL: Homepage, https://github.com/jul/bla
Keywords: LDAP,cli
Classifier: Development Status :: 4 - Beta
Classifier: Programming Language :: Python
Provides: blabing
Requires-Python: >=3.9
License-File: LICENSE.txt
Requires-Dist: ldap3
Requires-Dist: tempdir
Requires-Dist: PyYAML
Requires-Dist: ipython
Requires-Dist: pygments-ldif
Requires-Dist: flask
